{"NomeNen":[{"NomeHatsu":"Refor\u00E7adores","Caracter\u00EDsticas":"\u00C9 a habilidade de melhorar a f\u00EDsicalidade do pr\u00F3prio corpo ou de um objeto","Personalidade":"S\u00E3o simples e determinados","Exemplos":"Gon e Uvogin"},{"NomeHatsu":"Transmutadores","Caracter\u00EDsticas":"\u00C9 a habilidade de transformar aura em algo diferente ou imitar as caracter\u00EDsticas de algo, seja mat\u00E9ria s\u00F3lida ou n\u00E3o.","Personalidade":"S\u00E3o grandes mentirosos","Exemplos":"Kilua e Hisoka"},{"NomeHatsu":"Materializadores","Caracter\u00EDsticas":"Habilidade de criar objetos f\u00EDsicos a partir da pr\u00F3pria aura","Personalidade":"S\u00E3o sens\u00EDveis e nervosos","Exemplos":"Kaito e Koltopi"},{"NomeHatsu":"Emissores","Caracter\u00EDsticas":"\u00C9 a habilidade de separar a aura do corpo","Personalidade":"Impacientes e n\u00E3o prestam aten\u00E7\u00E3o em detalhes","Exemplos":"Razor e Senritsu"},{"NomeHatsu":"Especialistas","Caracter\u00EDsticas":"Tudo que n\u00E3o encaixa nas outras categorias","Personalidade":"Carism\u00E1ticos e independentes","Exemplos":"Neon e Kuroro"}]}